blockcheck-0.1.0.dist-info/METADATA
blockcheck-0.1.0.dist-info/WHEEL
blockcheck/__init__.py
blockcheck/blockcheck.cp312-win_amd64.pyd
blockcheck-0.1.0.dist-info/RECORD
