Metadata-Version: 2.4
Name: blockcheck
Version: 0.1.0
Summary: A Python package to check Bitcoin address balances using Blockchain.info API
Author-email: randyungaro <xrandyungarox@gmail.com>
License: MIT
Requires-Python: >=3.6
